{
  "collapse-filter": false,
  "search": "",
  "showTags": true,
  "showAttachments": true,
  "hideUnresolved": false,
  "showOrphans": true,
  "collapse-color-groups": false,
  "colorGroups": [
    {
      "query": "tag:#app  ",
      "color": {
        "a": 1,
        "rgb": 6443744
      }
    },
    {
      "query": "tag:#Error  ",
      "color": {
        "a": 1,
        "rgb": 14701145
      }
    },
    {
      "query": "tag:#desarrollo  ",
      "color": {
        "a": 1,
        "rgb": 13428121
      }
    },
    {
      "query": "tag:#pendiente  ",
      "color": {
        "a": 1,
        "rgb": 16582664
      }
    },
    {
      "query": "tag:#estructura  ",
      "color": {
        "a": 1,
        "rgb": 8192759
      }
    },
    {
      "query": "tag:#hospital  ",
      "color": {
        "a": 1,
        "rgb": 391726
      }
    },
    {
      "query": "tag:#SegElec  ",
      "color": {
        "a": 1,
        "rgb": 4391534
      }
    }
  ],
  "collapse-display": false,
  "showArrow": false,
  "textFadeMultiplier": -0.3,
  "nodeSizeMultiplier": 0.916666666666667,
  "lineSizeMultiplier": 0.916666666666667,
  "collapse-forces": false,
  "centerStrength": 0.625,
  "repelStrength": 8.95833333333333,
  "linkStrength": 0.192708333333333,
  "linkDistance": 145,
  "scale": 0.5087618855792565,
  "close": true
}